pysee/__init__.py
pysee/cli/__init__.py
pysee/cli/main.py
pysee/core/__init__.py
pysee/core/dashboard.py
pysee/core/data.py
pysee/panels/__init__.py
pysee/panels/base.py
pysee/panels/heatmap.py
pysee/panels/qc.py
pysee/panels/umap.py
pysee/panels/violin.py
pysee/utils/system_requirements.py
pysee_bio-0.1.3.dist-info/METADATA
pysee_bio-0.1.3.dist-info/WHEEL
pysee_bio-0.1.3.dist-info/entry_points.txt
pysee_bio-0.1.3.dist-info/top_level.txt
pysee_bio-0.1.3.dist-info/RECORD
