Metadata-Version: 2.4
Name: pysee-bio
Version: 0.1.3
Summary: Interactive, Reproducible Bioinformatics Visualization for Python
Home-page: https://github.com/pysee/pysee
Author: PySEE Contributors
Author-email: PySEE Contributors <pysee@example.com>
License: MIT
Classifier: Development Status :: 3 - Alpha
Classifier: Intended Audience :: Science/Research
Classifier: Topic :: Scientific/Engineering :: Bio-Informatics
Classifier: License :: OSI Approved :: MIT License
Classifier: Programming Language :: Python :: 3
Classifier: Programming Language :: Python :: 3.9
Classifier: Programming Language :: Python :: 3.10
Classifier: Programming Language :: Python :: 3.11
Classifier: Programming Language :: Python :: 3.12
Requires-Python: >=3.9
Requires-Dist: scanpy>=1.9.0
Requires-Dist: anndata>=0.8.0
Requires-Dist: pandas>=1.5.0
Requires-Dist: numpy>=1.21.0
Requires-Dist: scipy>=1.9.0
Requires-Dist: matplotlib>=3.5.0
Requires-Dist: seaborn>=0.11.0
Requires-Dist: plotly>=5.0.0
Requires-Dist: bokeh>=2.4.0
Requires-Dist: jupyter>=1.0.0
Requires-Dist: ipywidgets>=8.0.0
Requires-Dist: ipykernel>=6.0.0
Requires-Dist: python-igraph>=0.10.0
Requires-Dist: leidenalg>=0.10.0
Provides-Extra: dev
Requires-Dist: pytest>=7.0.0; extra == "dev"
Requires-Dist: black>=22.0.0; extra == "dev"
Requires-Dist: flake8>=5.0.0; extra == "dev"
Requires-Dist: mypy>=0.991; extra == "dev"
Requires-Dist: pre-commit>=3.0.0; extra == "dev"
Requires-Dist: isort>=5.0.0; extra == "dev"
Dynamic: author
Dynamic: home-page
Dynamic: requires-python
